{"topic": "AI Ethics", "generated_at": "2025-09-14T12:36:23+00:00", "series": [{"month": "2020-10", "post_count": 1, "avg_reactions": 20.0, "avg_comments": 0.0, "avg_restacks": 0.0, "avg_reactions_per_1k": 0.0, "avg_comments_per_1k": 0.0, "avg_restacks_per_1k": 0.0}, {"month": "2023-10", "post_count": 1, "avg_reactions": 10.0, "avg_comments": 0.0, "avg_restacks": 1.0, "avg_reactions_per_1k": 0.18181818181818182, "avg_comments_per_1k": 0.0, "avg_restacks_per_1k": 0.01818181818181818}, {"month": "2024-08", "post_count": 2, "avg_reactions": 2.5, "avg_comments": 4.0, "avg_restacks": 0.5, "avg_reactions_per_1k": 0.14214046822742477, "avg_comments_per_1k": 0.17391304347826086, "avg_restacks_per_1k": 0.021739130434782608}, {"month": "2025-01", "post_count": 1, "avg_reactions": 9.0, "avg_comments": 0.0, "avg_restacks": 1.0, "avg_reactions_per_1k": 6.0, "avg_comments_per_1k": 0.0, "avg_restacks_per_1k": 0.6666666666666666}, {"month": "2025-02", "post_count": 2, "avg_reactions": 23.0, "avg_comments": 2.0, "avg_restacks": 2.5, "avg_reactions_per_1k": 1.5991561181434597, "avg_comments_per_1k": 0.02531645569620253, "avg_restacks_per_1k": 0.6856540084388185}, {"month": "2025-03", "post_count": 4, "avg_reactions": 17.5, "avg_comments": 9.5, "avg_restacks": 4.0, "avg_reactions_per_1k": 0.7602239532619279, "avg_comments_per_1k": 0.12025316455696203, "avg_restacks_per_1k": 0.06669912366114898}, {"month": "2025-04", "post_count": 3, "avg_reactions": 52.0, "avg_comments": 11.0, "avg_restacks": 8.0, "avg_reactions_per_1k": 1.6982163406214041, "avg_comments_per_1k": 0.19629842731108552, "avg_restacks_per_1k": 0.36961386012018926}, {"month": "2025-05", "post_count": 12, "avg_reactions": 49.416666666666664, "avg_comments": 33.583333333333336, "avg_restacks": 6.833333333333333, "avg_reactions_per_1k": 2.060290864500522, "avg_comments_per_1k": 0.5030412860464566, "avg_restacks_per_1k": 0.6440029227017612}, {"month": "2025-06", "post_count": 10, "avg_reactions": 28.2, "avg_comments": 13.6, "avg_restacks": 2.6, "avg_reactions_per_1k": 4.030206003657242, "avg_comments_per_1k": 0.952426771713381, "avg_restacks_per_1k": 0.37221386811860746}, {"month": "2025-07", "post_count": 24, "avg_reactions": 29.041666666666668, "avg_comments": 12.583333333333334, "avg_restacks": 3.9583333333333335, "avg_reactions_per_1k": 2.997103972190278, "avg_comments_per_1k": 2.2814817390766757, "avg_restacks_per_1k": 0.6970096507028325}, {"month": "2025-08", "post_count": 48, "avg_reactions": 33.354166666666664, "avg_comments": 19.916666666666668, "avg_restacks": 5.375, "avg_reactions_per_1k": 1.45792128961792, "avg_comments_per_1k": 0.5417397752164378, "avg_restacks_per_1k": 0.27045781496280563}, {"month": "2025-09", "post_count": 8, "avg_reactions": 8.125, "avg_comments": 2.125, "avg_restacks": 2.0, "avg_reactions_per_1k": 1.9539141414141412, "avg_comments_per_1k": 1.1534576534576535, "avg_restacks_per_1k": 0.4215229215229215}]}