{"topic": "AI", "generated_at": "2025-09-14T12:36:23+00:00", "series": [{"month": "2022-08", "post_count": 1, "avg_reactions": 3.0, "avg_comments": 0.0, "avg_restacks": 0.0, "avg_reactions_per_1k": 0.13043478260869565, "avg_comments_per_1k": 0.0, "avg_restacks_per_1k": 0.0}, {"month": "2022-11", "post_count": 1, "avg_reactions": 1.0, "avg_comments": 0.0, "avg_restacks": 0.0, "avg_reactions_per_1k": 0.043478260869565216, "avg_comments_per_1k": 0.0, "avg_restacks_per_1k": 0.0}, {"month": "2023-02", "post_count": 1, "avg_reactions": 6.0, "avg_comments": 0.0, "avg_restacks": 0.0, "avg_reactions_per_1k": 0.038461538461538464, "avg_comments_per_1k": 0.0, "avg_restacks_per_1k": 0.0}, {"month": "2023-05", "post_count": 1, "avg_reactions": 0.0, "avg_comments": 0.0, "avg_restacks": 0.0, "avg_reactions_per_1k": 0.0, "avg_comments_per_1k": 0.0, "avg_restacks_per_1k": 0.0}, {"month": "2023-06", "post_count": 1, "avg_reactions": 0.0, "avg_comments": 0.0, "avg_restacks": 0.0, "avg_reactions_per_1k": 0.0, "avg_comments_per_1k": 0.0, "avg_restacks_per_1k": 0.0}, {"month": "2023-09", "post_count": 1, "avg_reactions": 3.0, "avg_comments": 0.0, "avg_restacks": 1.0, "avg_reactions_per_1k": 0.03529411764705882, "avg_comments_per_1k": 0.0, "avg_restacks_per_1k": 0.011764705882352941}, {"month": "2023-11", "post_count": 1, "avg_reactions": 0.0, "avg_comments": 0.0, "avg_restacks": 0.0, "avg_reactions_per_1k": 0.0, "avg_comments_per_1k": 0.0, "avg_restacks_per_1k": 0.0}, {"month": "2024-05", "post_count": 1, "avg_reactions": 3.0, "avg_comments": 8.0, "avg_restacks": 2.0, "avg_reactions_per_1k": 0.30000000000000004, "avg_comments_per_1k": 0.8, "avg_restacks_per_1k": 0.2}, {"month": "2024-06", "post_count": 1, "avg_reactions": 0.0, "avg_comments": 0.0, "avg_restacks": 0.0, "avg_reactions_per_1k": 0.0, "avg_comments_per_1k": 0.0, "avg_restacks_per_1k": 0.0}, {"month": "2024-07", "post_count": 2, "avg_reactions": 2.0, "avg_comments": 5.0, "avg_restacks": 0.5, "avg_reactions_per_1k": 0.08695652173913043, "avg_comments_per_1k": 0.21739130434782608, "avg_restacks_per_1k": 0.2631578947368421}, {"month": "2024-08", "post_count": 4, "avg_reactions": 3.75, "avg_comments": 2.25, "avg_restacks": 0.5, "avg_reactions_per_1k": 0.16304347826086957, "avg_comments_per_1k": 0.09782608695652173, "avg_restacks_per_1k": 0.021739130434782608}, {"month": "2024-09", "post_count": 3, "avg_reactions": 20.666666666666668, "avg_comments": 7.0, "avg_restacks": 1.6666666666666667, "avg_reactions_per_1k": 0.15065306852746466, "avg_comments_per_1k": 0.028806584362139922, "avg_restacks_per_1k": 0.22028859947327614}, {"month": "2024-10", "post_count": 5, "avg_reactions": 2.4, "avg_comments": 2.2, "avg_restacks": 0.0, "avg_reactions_per_1k": 0.41654638267910576, "avg_comments_per_1k": 0.09565217391304348, "avg_restacks_per_1k": 0.0}, {"month": "2024-11", "post_count": 3, "avg_reactions": 44.333333333333336, "avg_comments": 2.6666666666666665, "avg_restacks": 2.0, "avg_reactions_per_1k": 2.726449275362319, "avg_comments_per_1k": 0.14130434782608695, "avg_restacks_per_1k": 0.11865942028985506}, {"month": "2024-12", "post_count": 4, "avg_reactions": 14.25, "avg_comments": 11.75, "avg_restacks": 1.25, "avg_reactions_per_1k": 1.075310559006211, "avg_comments_per_1k": 1.1467391304347827, "avg_restacks_per_1k": 0.10892857142857143}, {"month": "2025-01", "post_count": 6, "avg_reactions": 30.5, "avg_comments": 2.6666666666666665, "avg_restacks": 1.5, "avg_reactions_per_1k": 0.624986849840651, "avg_comments_per_1k": 0.0, "avg_restacks_per_1k": 0.008788947677836566}, {"month": "2025-02", "post_count": 14, "avg_reactions": 47.357142857142854, "avg_comments": 6.142857142857143, "avg_restacks": 4.357142857142857, "avg_reactions_per_1k": 1.429216755983023, "avg_comments_per_1k": 0.0715914288347481, "avg_restacks_per_1k": 0.5629928974714894}, {"month": "2025-03", "post_count": 31, "avg_reactions": 42.096774193548384, "avg_comments": 9.96774193548387, "avg_restacks": 7.258064516129032, "avg_reactions_per_1k": 2.0410610631665214, "avg_comments_per_1k": 0.35234070693132774, "avg_restacks_per_1k": 0.43966783393867953}, {"month": "2025-04", "post_count": 33, "avg_reactions": 26.818181818181817, "avg_comments": 5.212121212121212, "avg_restacks": 5.0, "avg_reactions_per_1k": 1.6457866941475348, "avg_comments_per_1k": 0.2778269772682713, "avg_restacks_per_1k": 0.4860956170213648}, {"month": "2025-05", "post_count": 63, "avg_reactions": 25.285714285714285, "avg_comments": 3.1904761904761907, "avg_restacks": 4.809523809523809, "avg_reactions_per_1k": 1.7522456718724833, "avg_comments_per_1k": 0.5111024101969552, "avg_restacks_per_1k": 0.4291676924640721}, {"month": "2025-06", "post_count": 145, "avg_reactions": 25.951724137931034, "avg_comments": 4.3517241379310345, "avg_restacks": 3.5724137931034483, "avg_reactions_per_1k": 1.735998821961515, "avg_comments_per_1k": 0.5007690042957482, "avg_restacks_per_1k": 0.3380158141526653}, {"month": "2025-07", "post_count": 214, "avg_reactions": 28.845794392523363, "avg_comments": 7.789719626168225, "avg_restacks": 3.4485981308411215, "avg_reactions_per_1k": 2.046693380118837, "avg_comments_per_1k": 0.7532354026867597, "avg_restacks_per_1k": 0.5258530177459583}, {"month": "2025-08", "post_count": 348, "avg_reactions": 39.86206896551724, "avg_comments": 42.17816091954023, "avg_restacks": 3.810344827586207, "avg_reactions_per_1k": 2.4908307467870423, "avg_comments_per_1k": 0.9031864637857074, "avg_restacks_per_1k": 0.46687114963039567}, {"month": "2025-09", "post_count": 76, "avg_reactions": 42.078947368421055, "avg_comments": 26.82894736842105, "avg_restacks": 5.092105263157895, "avg_reactions_per_1k": 2.1156641570583608, "avg_comments_per_1k": 0.19568681654018732, "avg_restacks_per_1k": 0.3590091720431369}]}