{"topic": "data centers", "generated_at": "2025-09-14T12:36:23+00:00", "series": [{"month": "2024-12", "post_count": 2, "avg_reactions": 18.0, "avg_comments": 10.0, "avg_restacks": 1.0, "avg_reactions_per_1k": 1.603846153846154, "avg_comments_per_1k": 1.0, "avg_restacks_per_1k": 0.1}, {"month": "2025-01", "post_count": 1, "avg_reactions": 30.0, "avg_comments": 22.0, "avg_restacks": 4.0, "avg_reactions_per_1k": 0.0, "avg_comments_per_1k": 0.0, "avg_restacks_per_1k": 0.0}, {"month": "2025-04", "post_count": 1, "avg_reactions": 18.0, "avg_comments": 0.0, "avg_restacks": 1.0, "avg_reactions_per_1k": 1.3846153846153846, "avg_comments_per_1k": 0.0, "avg_restacks_per_1k": 0.07692307692307693}, {"month": "2025-05", "post_count": 3, "avg_reactions": 27.666666666666668, "avg_comments": 22.0, "avg_restacks": 3.3333333333333335, "avg_reactions_per_1k": 2.466666666666667, "avg_comments_per_1k": 2.2, "avg_restacks_per_1k": 0.2871794871794872}, {"month": "2025-06", "post_count": 5, "avg_reactions": 22.8, "avg_comments": 7.2, "avg_restacks": 3.2, "avg_reactions_per_1k": 1.700897435897436, "avg_comments_per_1k": 0.66, "avg_restacks_per_1k": 0.2652564102564102}, {"month": "2025-08", "post_count": 24, "avg_reactions": 17.875, "avg_comments": 1.5416666666666667, "avg_restacks": 1.1666666666666667, "avg_reactions_per_1k": 8.420903110047847, "avg_comments_per_1k": 0.8114035087719298, "avg_restacks_per_1k": 0.5711224082934608}]}