{"topic": "Home & Garden", "generated_at": "2025-09-14T12:36:23+00:00", "series": [{"month": "2023-11", "post_count": 1, "avg_reactions": 155.0, "avg_comments": 16.0, "avg_restacks": 1.0, "avg_reactions_per_1k": 2.9245283018867925, "avg_comments_per_1k": 0.3018867924528302, "avg_restacks_per_1k": 0.018867924528301886}, {"month": "2024-02", "post_count": 1, "avg_reactions": 11.0, "avg_comments": 6.0, "avg_restacks": 0.0, "avg_reactions_per_1k": 0.0, "avg_comments_per_1k": 0.0, "avg_restacks_per_1k": 0.0}, {"month": "2024-06", "post_count": 1, "avg_reactions": 5.0, "avg_comments": 2.0, "avg_restacks": 0.0, "avg_reactions_per_1k": 2500.0, "avg_comments_per_1k": 1000.0, "avg_restacks_per_1k": 0.0}, {"month": "2024-10", "post_count": 1, "avg_reactions": 21.0, "avg_comments": 9.0, "avg_restacks": 3.0, "avg_reactions_per_1k": 8.4, "avg_comments_per_1k": 3.6, "avg_restacks_per_1k": 1.2000000000000002}, {"month": "2024-12", "post_count": 1, "avg_reactions": 31.0, "avg_comments": 15.0, "avg_restacks": 2.0, "avg_reactions_per_1k": 6.888888888888888, "avg_comments_per_1k": 3.333333333333333, "avg_restacks_per_1k": 0.4444444444444444}, {"month": "2025-01", "post_count": 2, "avg_reactions": 33.0, "avg_comments": 7.0, "avg_restacks": 0.0, "avg_reactions_per_1k": 3.7602941176470592, "avg_comments_per_1k": 1.258823529411765, "avg_restacks_per_1k": 0.0}, {"month": "2025-02", "post_count": 4, "avg_reactions": 15.25, "avg_comments": 3.25, "avg_restacks": 1.0, "avg_reactions_per_1k": 0.8226540616246498, "avg_comments_per_1k": 0.04779411764705882, "avg_restacks_per_1k": 0.13333333333333333}, {"month": "2025-03", "post_count": 6, "avg_reactions": 23.666666666666668, "avg_comments": 13.833333333333334, "avg_restacks": 0.6666666666666666, "avg_reactions_per_1k": 1.8809523809523812, "avg_comments_per_1k": 1.0532679738562092, "avg_restacks_per_1k": 0.0472922502334267}, {"month": "2025-04", "post_count": 5, "avg_reactions": 14.0, "avg_comments": 4.6, "avg_restacks": 0.0, "avg_reactions_per_1k": 0.3711523752091703, "avg_comments_per_1k": 0.34830966869506425, "avg_restacks_per_1k": 0.0}, {"month": "2025-05", "post_count": 11, "avg_reactions": 58.54545454545455, "avg_comments": 9.0, "avg_restacks": 2.272727272727273, "avg_reactions_per_1k": 3.9837437924394448, "avg_comments_per_1k": 0.5446640316205533, "avg_restacks_per_1k": 0.17523056653491434}, {"month": "2025-06", "post_count": 18, "avg_reactions": 57.44444444444444, "avg_comments": 19.333333333333332, "avg_restacks": 1.0555555555555556, "avg_reactions_per_1k": 5.6022251263939244, "avg_comments_per_1k": 1.8561707403139627, "avg_restacks_per_1k": 0.1462097450218328}, {"month": "2025-07", "post_count": 27, "avg_reactions": 42.888888888888886, "avg_comments": 15.25925925925926, "avg_restacks": 1.1481481481481481, "avg_reactions_per_1k": 3.7676847224019596, "avg_comments_per_1k": 1.9398452887019653, "avg_restacks_per_1k": 0.08845065967743986}, {"month": "2025-08", "post_count": 30, "avg_reactions": 103.3, "avg_comments": 24.8, "avg_restacks": 10.933333333333334, "avg_reactions_per_1k": 3.7810252587722175, "avg_comments_per_1k": 0.9628777892710796, "avg_restacks_per_1k": 0.18707810355915702}, {"month": "2025-09", "post_count": 15, "avg_reactions": 14.466666666666667, "avg_comments": 4.933333333333334, "avg_restacks": 0.3333333333333333, "avg_reactions_per_1k": 1.8324585407712344, "avg_comments_per_1k": 0.7289208220400171, "avg_restacks_per_1k": 0.009387949511788521}]}