{"topic": "LGBTQ+", "generated_at": "2025-09-14T12:36:23+00:00", "series": [{"month": "2020-07", "post_count": 1, "avg_reactions": 10.0, "avg_comments": 0.0, "avg_restacks": 3.0, "avg_reactions_per_1k": 0.05025125628140704, "avg_comments_per_1k": 0.0, "avg_restacks_per_1k": 0.01507537688442211}, {"month": "2022-04", "post_count": 1, "avg_reactions": 342.0, "avg_comments": 14.0, "avg_restacks": 12.0, "avg_reactions_per_1k": 31.090909090909093, "avg_comments_per_1k": 1.2727272727272727, "avg_restacks_per_1k": 1.0909090909090908}, {"month": "2022-06", "post_count": 1, "avg_reactions": 824.0, "avg_comments": 23.0, "avg_restacks": 35.0, "avg_reactions_per_1k": 74.9090909090909, "avg_comments_per_1k": 2.090909090909091, "avg_restacks_per_1k": 3.181818181818182}, {"month": "2022-08", "post_count": 2, "avg_reactions": 15.5, "avg_comments": 0.0, "avg_restacks": 0.0, "avg_reactions_per_1k": 8.157894736842106, "avg_comments_per_1k": 0.0, "avg_restacks_per_1k": 0.0}, {"month": "2022-09", "post_count": 1, "avg_reactions": 345.0, "avg_comments": 9.0, "avg_restacks": 17.0, "avg_reactions_per_1k": 31.363636363636363, "avg_comments_per_1k": 0.8181818181818182, "avg_restacks_per_1k": 1.5454545454545454}, {"month": "2022-12", "post_count": 3, "avg_reactions": 19.333333333333332, "avg_comments": 4.333333333333333, "avg_restacks": 0.3333333333333333, "avg_reactions_per_1k": 13.748006379585327, "avg_comments_per_1k": 3.5566188197767143, "avg_restacks_per_1k": 0.30303030303030304}, {"month": "2023-03", "post_count": 2, "avg_reactions": 11.0, "avg_comments": 0.0, "avg_restacks": 0.0, "avg_reactions_per_1k": 11.578947368421051, "avg_comments_per_1k": 0.0, "avg_restacks_per_1k": 0.0}, {"month": "2023-04", "post_count": 2, "avg_reactions": 10.5, "avg_comments": 5.0, "avg_restacks": 1.5, "avg_reactions_per_1k": 5.271778584392014, "avg_comments_per_1k": 2.631578947368421, "avg_restacks_per_1k": 0.7894736842105263}, {"month": "2023-05", "post_count": 1, "avg_reactions": 5.0, "avg_comments": 5.0, "avg_restacks": 0.0, "avg_reactions_per_1k": 0.0, "avg_comments_per_1k": 0.0, "avg_restacks_per_1k": 0.0}, {"month": "2024-04", "post_count": 2, "avg_reactions": 16.0, "avg_comments": 1.0, "avg_restacks": 1.5, "avg_reactions_per_1k": 0.39473684210526316, "avg_comments_per_1k": 0.05263157894736842, "avg_restacks_per_1k": 0.05263157894736842}, {"month": "2024-05", "post_count": 1, "avg_reactions": 15.0, "avg_comments": 6.0, "avg_restacks": 0.0, "avg_reactions_per_1k": 0.2727272727272727, "avg_comments_per_1k": 0.10909090909090909, "avg_restacks_per_1k": 0.0}, {"month": "2024-06", "post_count": 2, "avg_reactions": 8.5, "avg_comments": 3.0, "avg_restacks": 0.0, "avg_reactions_per_1k": 0.7894736842105263, "avg_comments_per_1k": 0.3157894736842105, "avg_restacks_per_1k": 0.0}, {"month": "2024-07", "post_count": 1, "avg_reactions": 12.0, "avg_comments": 3.0, "avg_restacks": 1.0, "avg_reactions_per_1k": 0.0, "avg_comments_per_1k": 0.0, "avg_restacks_per_1k": 0.0}, {"month": "2024-08", "post_count": 1, "avg_reactions": 12.0, "avg_comments": 0.0, "avg_restacks": 0.0, "avg_reactions_per_1k": 8.0, "avg_comments_per_1k": 0.0, "avg_restacks_per_1k": 0.0}, {"month": "2024-11", "post_count": 1, "avg_reactions": 681.0, "avg_comments": 398.0, "avg_restacks": 81.0, "avg_reactions_per_1k": 162.14285714285714, "avg_comments_per_1k": 94.76190476190476, "avg_restacks_per_1k": 19.285714285714285}, {"month": "2024-12", "post_count": 5, "avg_reactions": 103.8, "avg_comments": 40.6, "avg_restacks": 14.0, "avg_reactions_per_1k": 16.658709273182957, "avg_comments_per_1k": 7.557644110275689, "avg_restacks_per_1k": 2.4282581453634084}, {"month": "2025-01", "post_count": 7, "avg_reactions": 116.57142857142857, "avg_comments": 26.714285714285715, "avg_restacks": 12.285714285714286, "avg_reactions_per_1k": 50.96036779757709, "avg_comments_per_1k": 7.002597402597402, "avg_restacks_per_1k": 7.558522098056981}, {"month": "2025-02", "post_count": 8, "avg_reactions": 91.375, "avg_comments": 27.125, "avg_restacks": 12.75, "avg_reactions_per_1k": 23.289423855277512, "avg_comments_per_1k": 6.681327209375991, "avg_restacks_per_1k": 4.06090169992609}, {"month": "2025-03", "post_count": 7, "avg_reactions": 121.42857142857143, "avg_comments": 43.57142857142857, "avg_restacks": 20.571428571428573, "avg_reactions_per_1k": 20.669980092307927, "avg_comments_per_1k": 6.567203500641448, "avg_restacks_per_1k": 2.963513033939863}, {"month": "2025-04", "post_count": 7, "avg_reactions": 72.14285714285714, "avg_comments": 24.142857142857142, "avg_restacks": 11.714285714285714, "avg_reactions_per_1k": 13.725316756414317, "avg_comments_per_1k": 5.156987118572484, "avg_restacks_per_1k": 2.0829967796431212}, {"month": "2025-05", "post_count": 15, "avg_reactions": 539.4666666666667, "avg_comments": 63.46666666666667, "avg_restacks": 85.2, "avg_reactions_per_1k": 18.254477197386475, "avg_comments_per_1k": 3.829294120830428, "avg_restacks_per_1k": 2.024573055028463}, {"month": "2025-06", "post_count": 36, "avg_reactions": 192.47222222222223, "avg_comments": 76.22222222222223, "avg_restacks": 26.555555555555557, "avg_reactions_per_1k": 11.760212013251222, "avg_comments_per_1k": 3.8514816811837562, "avg_restacks_per_1k": 1.686965518854391}, {"month": "2025-07", "post_count": 42, "avg_reactions": 349.2857142857143, "avg_comments": 77.28571428571429, "avg_restacks": 61.57142857142857, "avg_reactions_per_1k": 942.2693273834706, "avg_comments_per_1k": 127.75988706958218, "avg_restacks_per_1k": 86.89476069762529}, {"month": "2025-08", "post_count": 68, "avg_reactions": 231.3235294117647, "avg_comments": 40.220588235294116, "avg_restacks": 40.76470588235294, "avg_reactions_per_1k": 444.01696921919296, "avg_comments_per_1k": 80.02519110324748, "avg_restacks_per_1k": 36.09317000267996}, {"month": "2025-09", "post_count": 23, "avg_reactions": 246.2173913043478, "avg_comments": 94.1304347826087, "avg_restacks": 44.130434782608695, "avg_reactions_per_1k": 8.753175291331626, "avg_comments_per_1k": 3.7933876111325553, "avg_restacks_per_1k": 1.099443111260732}]}