{"topic": "Monetary Policy", "generated_at": "2025-09-14T12:36:23+00:00", "series": [{"month": "2022-02", "post_count": 1, "avg_reactions": 0.0, "avg_comments": 0.0, "avg_restacks": 0.0, "avg_reactions_per_1k": 0.0, "avg_comments_per_1k": 0.0, "avg_restacks_per_1k": 0.0}, {"month": "2024-04", "post_count": 1, "avg_reactions": 32.0, "avg_comments": 4.0, "avg_restacks": 4.0, "avg_reactions_per_1k": 2.2857142857142856, "avg_comments_per_1k": 0.2857142857142857, "avg_restacks_per_1k": 0.2857142857142857}, {"month": "2024-06", "post_count": 1, "avg_reactions": 27.0, "avg_comments": 23.0, "avg_restacks": 4.0, "avg_reactions_per_1k": 1.9285714285714284, "avg_comments_per_1k": 1.6428571428571428, "avg_restacks_per_1k": 0.2857142857142857}, {"month": "2024-12", "post_count": 1, "avg_reactions": 89.0, "avg_comments": 23.0, "avg_restacks": 22.0, "avg_reactions_per_1k": 6.357142857142857, "avg_comments_per_1k": 1.6428571428571428, "avg_restacks_per_1k": 1.5714285714285714}, {"month": "2025-04", "post_count": 4, "avg_reactions": 70.75, "avg_comments": 14.5, "avg_restacks": 15.5, "avg_reactions_per_1k": 9.311154598825832, "avg_comments_per_1k": 1.3962818003913893, "avg_restacks_per_1k": 2.568982387475538}, {"month": "2025-05", "post_count": 6, "avg_reactions": 31.333333333333332, "avg_comments": 7.333333333333333, "avg_restacks": 0.5, "avg_reactions_per_1k": 3.0508474576271185, "avg_comments_per_1k": 0.5084745762711864, "avg_restacks_per_1k": 0.1694915254237288}, {"month": "2025-06", "post_count": 9, "avg_reactions": 35.333333333333336, "avg_comments": 7.777777777777778, "avg_restacks": 1.3333333333333333, "avg_reactions_per_1k": 2.9579509166834153, "avg_comments_per_1k": 0.5514466700907379, "avg_restacks_per_1k": 0.08168642951251646}, {"month": "2025-07", "post_count": 10, "avg_reactions": 67.9, "avg_comments": 17.7, "avg_restacks": 3.5, "avg_reactions_per_1k": 2.525296442687747, "avg_comments_per_1k": 0.5737812911725955, "avg_restacks_per_1k": 0.10606060606060605}, {"month": "2025-08", "post_count": 34, "avg_reactions": 68.38235294117646, "avg_comments": 13.735294117647058, "avg_restacks": 6.323529411764706, "avg_reactions_per_1k": 2.7742674973578207, "avg_comments_per_1k": 1.2414145953120954, "avg_restacks_per_1k": 0.12040014683773449}, {"month": "2025-09", "post_count": 12, "avg_reactions": 20.5, "avg_comments": 7.833333333333333, "avg_restacks": 2.5833333333333335, "avg_reactions_per_1k": 2.769733436853002, "avg_comments_per_1k": 1.375386518243661, "avg_restacks_per_1k": 0.25307282003710574}]}