{"topic": "Polarization", "generated_at": "2025-09-14T12:36:23+00:00", "series": [{"month": "2023-01", "post_count": 1, "avg_reactions": 21.0, "avg_comments": 8.0, "avg_restacks": 0.0, "avg_reactions_per_1k": 16.153846153846153, "avg_comments_per_1k": 6.153846153846154, "avg_restacks_per_1k": 0.0}, {"month": "2023-08", "post_count": 1, "avg_reactions": 11.0, "avg_comments": 4.0, "avg_restacks": 3.0, "avg_reactions_per_1k": 2.619047619047619, "avg_comments_per_1k": 0.9523809523809523, "avg_restacks_per_1k": 0.7142857142857142}, {"month": "2024-10", "post_count": 1, "avg_reactions": 11.0, "avg_comments": 4.0, "avg_restacks": 4.0, "avg_reactions_per_1k": 0.7333333333333333, "avg_comments_per_1k": 0.26666666666666666, "avg_restacks_per_1k": 0.26666666666666666}, {"month": "2025-03", "post_count": 3, "avg_reactions": 19.333333333333332, "avg_comments": 7.0, "avg_restacks": 4.333333333333333, "avg_reactions_per_1k": 1.9401129943502824, "avg_comments_per_1k": 0.6037664783427495, "avg_restacks_per_1k": 0.35743879472693035}, {"month": "2025-07", "post_count": 2, "avg_reactions": 75.5, "avg_comments": 59.5, "avg_restacks": 13.0, "avg_reactions_per_1k": 19.076887232059647, "avg_comments_per_1k": 19.191985088536814, "avg_restacks_per_1k": 3.9857875116495807}, {"month": "2025-08", "post_count": 1, "avg_reactions": 13.0, "avg_comments": 2.0, "avg_restacks": 2.0, "avg_reactions_per_1k": 1.1818181818181819, "avg_comments_per_1k": 0.18181818181818182, "avg_restacks_per_1k": 0.18181818181818182}]}