{"topic": "Sales", "generated_at": "2025-09-14T12:36:23+00:00", "series": [{"month": "2021-01", "post_count": 1, "avg_reactions": 0.0, "avg_comments": 0.0, "avg_restacks": 0.0, "avg_reactions_per_1k": 0.0, "avg_comments_per_1k": 0.0, "avg_restacks_per_1k": 0.0}, {"month": "2023-01", "post_count": 4, "avg_reactions": 2.0, "avg_comments": 0.0, "avg_restacks": 0.0, "avg_reactions_per_1k": 0.0, "avg_comments_per_1k": 0.0, "avg_restacks_per_1k": 0.0}, {"month": "2023-02", "post_count": 1, "avg_reactions": 0.0, "avg_comments": 0.0, "avg_restacks": 0.0, "avg_reactions_per_1k": 0.0, "avg_comments_per_1k": 0.0, "avg_restacks_per_1k": 0.0}, {"month": "2023-03", "post_count": 3, "avg_reactions": 4.666666666666667, "avg_comments": 0.0, "avg_restacks": 0.0, "avg_reactions_per_1k": 0.0, "avg_comments_per_1k": 0.0, "avg_restacks_per_1k": 0.0}, {"month": "2023-04", "post_count": 3, "avg_reactions": 2.6666666666666665, "avg_comments": 0.6666666666666666, "avg_restacks": 0.0, "avg_reactions_per_1k": 0.0, "avg_comments_per_1k": 0.0, "avg_restacks_per_1k": 0.0}, {"month": "2023-05", "post_count": 1, "avg_reactions": 7.0, "avg_comments": 4.0, "avg_restacks": 0.0, "avg_reactions_per_1k": 0.0, "avg_comments_per_1k": 0.0, "avg_restacks_per_1k": 0.0}, {"month": "2023-07", "post_count": 1, "avg_reactions": 3.0, "avg_comments": 0.0, "avg_restacks": 0.0, "avg_reactions_per_1k": 0.0, "avg_comments_per_1k": 0.0, "avg_restacks_per_1k": 0.0}, {"month": "2023-10", "post_count": 1, "avg_reactions": 16.0, "avg_comments": 2.0, "avg_restacks": 0.0, "avg_reactions_per_1k": 0.18604651162790697, "avg_comments_per_1k": 0.023255813953488372, "avg_restacks_per_1k": 0.0}, {"month": "2024-02", "post_count": 2, "avg_reactions": 4.5, "avg_comments": 0.0, "avg_restacks": 0.5, "avg_reactions_per_1k": 0.0, "avg_comments_per_1k": 0.0, "avg_restacks_per_1k": 0.0}, {"month": "2024-03", "post_count": 1, "avg_reactions": 11.0, "avg_comments": 0.0, "avg_restacks": 0.0, "avg_reactions_per_1k": 0.0, "avg_comments_per_1k": 0.0, "avg_restacks_per_1k": 0.0}, {"month": "2024-07", "post_count": 1, "avg_reactions": 39.0, "avg_comments": 13.0, "avg_restacks": 1.0, "avg_reactions_per_1k": 0.0, "avg_comments_per_1k": 0.0, "avg_restacks_per_1k": 0.0}, {"month": "2024-08", "post_count": 1, "avg_reactions": 17.0, "avg_comments": 3.0, "avg_restacks": 0.0, "avg_reactions_per_1k": 0.0, "avg_comments_per_1k": 0.0, "avg_restacks_per_1k": 0.0}, {"month": "2024-11", "post_count": 2, "avg_reactions": 7.0, "avg_comments": 0.0, "avg_restacks": 0.0, "avg_reactions_per_1k": 1.267605633802817, "avg_comments_per_1k": 0.0, "avg_restacks_per_1k": 0.0}, {"month": "2024-12", "post_count": 1, "avg_reactions": 6.0, "avg_comments": 0.0, "avg_restacks": 1.0, "avg_reactions_per_1k": 0.8450704225352113, "avg_comments_per_1k": 0.0, "avg_restacks_per_1k": 0.14084507042253522}, {"month": "2025-03", "post_count": 1, "avg_reactions": 0.0, "avg_comments": 0.0, "avg_restacks": 0.0, "avg_reactions_per_1k": 0.0, "avg_comments_per_1k": 0.0, "avg_restacks_per_1k": 0.0}, {"month": "2025-04", "post_count": 3, "avg_reactions": 3.3333333333333335, "avg_comments": 2.0, "avg_restacks": 0.6666666666666666, "avg_reactions_per_1k": 0.717948717948718, "avg_comments_per_1k": 0.2564102564102564, "avg_restacks_per_1k": 0.08547008547008546}, {"month": "2025-05", "post_count": 5, "avg_reactions": 48.6, "avg_comments": 44.2, "avg_restacks": 3.2, "avg_reactions_per_1k": 1.561746224789703, "avg_comments_per_1k": 0.44367588932806323, "avg_restacks_per_1k": 0.11357302118171683}, {"month": "2025-06", "post_count": 9, "avg_reactions": 2.2222222222222223, "avg_comments": 0.5555555555555556, "avg_restacks": 0.1111111111111111, "avg_reactions_per_1k": 0.1185897435897436, "avg_comments_per_1k": 0.27884615384615385, "avg_restacks_per_1k": 0.003787878787878788}, {"month": "2025-07", "post_count": 32, "avg_reactions": 13.03125, "avg_comments": 1.9375, "avg_restacks": 0.96875, "avg_reactions_per_1k": 1.7273055675115172, "avg_comments_per_1k": 0.07177766564815594, "avg_restacks_per_1k": 0.22073127923284205}, {"month": "2025-08", "post_count": 32, "avg_reactions": 11.125, "avg_comments": 2.0625, "avg_restacks": 1.0625, "avg_reactions_per_1k": 1.6777268721160379, "avg_comments_per_1k": 0.17746944491466968, "avg_restacks_per_1k": 0.4524857169248836}, {"month": "2025-09", "post_count": 11, "avg_reactions": 6.636363636363637, "avg_comments": 2.3636363636363638, "avg_restacks": 0.8181818181818182, "avg_reactions_per_1k": 2.1468681443471853, "avg_comments_per_1k": 1.0389789439684645, "avg_restacks_per_1k": 0.45484197170524543}]}